Workbook

Sheet catalog
B1: Nombre | C1: Categoría | D1: Descripción | E1: Precio | F1: URL de Imagen
A2: 1 | B2: Nuez Mariposa Extra Light x 1 Kg | C2: Frutos Secos | D2: Detallar con palabras claras | E2: 20500 | F2: https://cdn.newgarden.com.ar/media/catalog/product/cache/dda7253a1a2f6711745de410175d10f8/n/u/nuez-pelada-cuartillo-extra-light_1_2_1_1.jpg
A3: =A2+1 -> 2 | B3: Almendra Non Pareil 27/30 x 1 Kg | C3: Frutos Secos | D3: Detallar con palabras claras | E3: 23000 | F3: https://encrypted-tbn0.gstatic.com/images?q=tbn:ANd9GcTnYmm3nBskRSQNDC7mbDaylPr-fLeZ5s2BHQ&s
A4: =A3+1 -> 3 | B4: Mani tostado con y sin sal PREMIUM x 1 Kg | C4: Frutos Secos | D4: Detallar con palabras claras | E4: 3000 | F4: https://cdn.newgarden.com.ar/media/catalog/product/cache/dda7253a1a2f6711745de410175d10f8/1/3/13089-mani-repelado-salado-y-tostado_1.jpg
A5: 4 | B5: Nuez Pecan x 1 Kg | C5: Frutos Secos | D5: Detallar con palabras claras | E5: 34600 | F5: https://cdn.shopify.com/s/files/1/1699/9375/files/la-nuez-pecan-ayuda-a-adelgazar_large.jpg?v=1499651301
A6: =A5+1 -> 5 | B6: Cajú W4 brasilero x 1 Kg | C6: Frutos Secos | D6: Detallar con palabras claras | E6: 19500 | F6: https://dcdn-us.mitiendanube.com/stores/001/569/510/products/_68y17isb6-fe1989881887e9785716430667084431-1024-1024.webp
A7: 6 | B7: Caju Tostadas con sal y sin sal 1kg | C7: Frutos Secos | E7: 20000 | F7: https://ketoandco.com.ar/wp-content/uploads/2024/08/castanas-de-caju-tostadas-y-saladas-2.png
A8: 7 | B8: Castañas de PARA x 1 Kg | C8: Frutos Secos | D8: Detallar con palabras claras | E8: 40200 | F8: https://cdn.newgarden.com.ar/media/catalog/product/cache/dda7253a1a2f6711745de410175d10f8/c/a/castanas-de-para-1-kg.jpg
A9: =A8+1 -> 8 | B9: Avellanas grandes x 1 Kg | C9: Frutos Secos | D9: Detallar con palabras claras | E9: 33200 | F9: https://tse2.mm.bing.net/th/id/OIP.EUdZVDmCv6FQwUlFKj3oMgHaE7?pid=Api&P=0&h=180
A10: 9 | B10: Pasas Rubia 1kg | C10: Frutos Secos | E10: 8200 | F10: https://cdn.newgarden.com.ar/media/catalog/product/cache/dda7253a1a2f6711745de410175d10f8/p/a/pasas-de-uva-rubias-premium-x-1kg.jpg
A11: =A10+1 -> 10 | B11: Pistacho salado con cascara x 1 Kg | C11: Frutos Secos | D11: Detallar con palabras claras | E11: 41000 | F11: https://cdn.newgarden.com.ar/media/catalog/product/cache/dda7253a1a2f6711745de410175d10f8/p/i/pistacho-con-cascara-salado-y-tostado-1kg.jpg
A12: 11 | B12: Maiz Frito salado x 1kg | C12: Frutos Secos | E12: 12000 | F12: https://tse3.mm.bing.net/th/id/OIP.w6yQYT_irw2zFRcafVuuFQAAAA?pid=Api&P=0&h=180
A13: =A11+1 -> 11 | B13: Mix criollo o Runner (Nuez cuartos , almendra, cajú, mani, pasas rubias y morochas) x 1kg | C13: Mix de Frutos secos | E13: 8200 | F13: https://encrypted-tbn0.gstatic.com/images?q=tbn:ANd9GcSKpfMEboVqmOHd2ilCkB_E-_hlK6NGs4wdZg&s
A14: 12 | B14: Mix criollo o Runner SIN MANI (Almendra, nuez, pasas rubias, pasas morochas y caju) 1kg | C14: Mix de Frutos secos | E14: 11700 | F14: https://acdn-us.mitiendanube.com/stores/001/229/173/products/mix-de-frutos-secos-con-pasas-12-kg-d_nq_np_589905-mla25107800259_102016-f1-799a1be3d88edbecbb15945260039537-480-0.jpg
A15: 13 | B15: Mix premium gourmet (Cajú, almendras, nueces y avellanas) x 1kg | C15: Mix de Frutos secos | E15: 23000 | F15: https://acdn-us.mitiendanube.com/stores/001/184/135/products/11-30087acda95d00a49316263074834401-640-0.webp
A16: 14 | B16: Mix europeo (Almendra, nuez, mani y caju) 1kg | C16: Mix de Frutos secos | E16: 12000 | F16: https://acdn-us.mitiendanube.com/stores/001/040/363/products/s-botanica-protectos-solar-fps-30-125ml-611-6b43b3b9208898d57c16717359401681-640-0.png
A17: 15 | B17: Mix criollo o runner con bananitas (Cajú, almendras, nueces, mani, pasas rubias y morochas, bananitas) | C17: Mix de Frutos secos | E17: 8400 | F17: https://http2.mlstatic.com/D_NQ_NP_600579-MLA53014366217_122022-O.webp
A18: =A17+1 -> 16 | B18: Mix cervecero (semillas peladas de girasol y de zapallo, castañas de cajú saladas, maní salado, maní japonés) 1kg | C18: Mix de Frutos secos | E18: 6300 | F18: https://d22fxaf9t8d39k.cloudfront.net/1383ba2a1c02bff5e680d91b32794476f4a03c7f91c4bd15de989ce8bb01e8e565493.png
A19: 17 | B19: Mix Berry ( Arándanos, cerezas, frutillas, nueces, cajú, almendras, coco en escamas y pasas) 1Kg | C19: Mix Frutos secos | E19: 17500 | F19: https://d22fxaf9t8d39k.cloudfront.net/66157a64ab633490eb331455e87ec03e4ce8cac0788ecf398aee49548d7548f465493.jpeg
A20: 18 | B20: Mix Pan Dulce | C20: Mix Frutos secos | E20: 11400 | F20: https://tse3.mm.bing.net/th/id/OIP.ekOVbwPBYW8BCYqov8csBgHaFj?pid=Api&P=0&h=180
A21: 18 | B21: Bananas disecadas x 1kg | C21: Frutas Disecadas | E21: 12000 | F21: https://tse2.mm.bing.net/th/id/OIP.WztaZHMqZeBta6F1Qf1uLwHaHa?pid=Api&P=0&h=180
A22: =A21+1 -> 19 | B22: Damasco turco grande x 1kg | C22: Frutas Disecadas | E22: 42000 | F22: https://cdn.newgarden.com.ar/media/catalog/product/cache/dda7253a1a2f6711745de410175d10f8/d/a/damascos-turcos-gigantes.jpg
A23: =A22+1 -> 20 | B23: Tomates deshidratados x 1kg | C23: Frutas Disecadas | E23: 15600 | F23: https://www.oestepizzaparty.com.ar/wp-content/uploads/2024/07/TOMATE-SECO.jpg
A24: 21 | B24: Peras x 1kg | C24: Frutas Disecadas | E24: 12500 | F24: https://tse3.mm.bing.net/th/id/OIP.zF-rlypNt8a3Ez0oYfijEAHaHa?pid=Api&P=0&h=180
A25: 22 | B25: Durazno Extra Grandes x 1kg | C25: Frutas Disecadas | E25: 18000 | F25: https://frutaslosnogales.com.ar/wp-content/uploads/2017/10/damascos-desecados.jpg
A26: 23 | B26: Ciruelas d Agen sin carozo x 1kg | C26: Frutas Disecadas | E26: 7500 | F26: https://http2.mlstatic.com/D_NQ_NP_817799-MLA49745917640_042022-O.webp
A27: =A26+1 -> 24 | B27: Arandanos | C27: Frutas Disecadas | E27: 13500 | F27: https://http2.mlstatic.com/D_NQ_NP_971630-MLA43638879754_092020-O.webp
A28: =A27+1 -> 25 | B28: Higos negros x 5kg | C28: Frutas Disecadas | E28: 47000 | F28: https://encrypted-tbn0.gstatic.com/images?q=tbn:ANd9GcS8dLvMpss83GZFYyFV7I6LpVznhQOKnMXEzQ&s
A29: =A28+1 -> 26 | B29: Datiles Egipto Caja 1 kg OFERTA | C29: Frutas Disecadas | E29: 8000 | F29: https://http2.mlstatic.com/D_NQ_NP_708601-MLA78585683115_082024-O.webp
B30: datiles Argelia | C30: frutas Disecadas | E30: 11000
A31: =A29+1 -> 27 | B31: Mix de semillas (Lino, girasol, sésamo) x 1kg | C31: Semillas Premium | E31: 4000 | F31: https://encrypted-tbn0.gstatic.com/images?q=tbn:ANd9GcTglzHWASxwluXIIkarYSwqpvnGgcZeuCAcLg&s
A32: =A31+1 -> 28 | B32: Lino x 1Kg | C32: Semillas Premium | E32: 3300 | F32: https://acdn-us.mitiendanube.com/stores/002/625/145/products/granola-exotica-2023-04-03t151215-6301-3106e1387bb613118416805456176298-1024-1024.jpg
A33: =A32+1 -> 29 | B33: Chia premium x 1Kg | C33: Semillas Premium | E33: 8700 | F33: https://http2.mlstatic.com/D_NQ_NP_894603-MLA43239351703_082020-O.webp
A34: =A33+1 -> 30 | B34: Sésamo integral x 1Kg | C34: Semillas Premium | E34: 5800 | F34: https://acdn-us.mitiendanube.com/stores/139/211/products/si1-5f39e3dbf951b2058416613695784776-640-0.jpg
A35: =A34+1 -> 31 | B35: Sesamo blanco x 1Kg | C35: Semillas Premium | E35: 10000 | F35: https://encrypted-tbn0.gstatic.com/images?q=tbn:ANd9GcQntFNQLSfcCRPYfdDWENnN-nnjkiXEd5X_rg&s
A36: =A35+1 -> 32 | B36: Girasol x 1Kg | C36: Semillas Premium | E36: 4100 | F36: https://cdn.newgarden.com.ar/media/catalog/product/cache/dda7253a1a2f6711745de410175d10f8/s/e/semillas-de-girasol.jpg
A37: =A36+1 -> 33 | B37: Quinoa x 1Kg | C37: Semillas Premium | E37: 12400 | F37: https://encrypted-tbn0.gstatic.com/images?q=tbn:ANd9GcSG1kARLaOIE7pGoafKjoedBbAX8hILHyNDMA&s
A38: =A37+1 -> 34 | B38: Zapallo x 1Kg | C38: Semillas Premium | E38: 14000 | F38: https://encrypted-tbn0.gstatic.com/images?q=tbn:ANd9GcTPwa8YpJ2Ttnds1LqAjpNrlaMFFdLbLeE9nw&s
B39: Arroz Yamani- OFERTA- | C39: Arroz | E39: 3500 | F39: https://tse1.mm.bing.net/th/id/OIP.T_wgPNv93guoZVlYExjQhwAAAA?pid=Api&P=0&h=180
A40: =A38+1 -> 35 | F40: https://cdn.newgarden.com.ar/media/catalog/product/cache/dda7253a1a2f6711745de410175d10f8/h/a/harina-de-avena-x-1-kg.jpg
A41: =A40+1 -> 36 | B41: Harina de coco x 1Kg | C41: Harinas | E41: 5800 | F41: https://cdn.newgarden.com.ar/media/catalog/product/cache/dda7253a1a2f6711745de410175d10f8/h/a/harina-de-coco-x-1-kg_1.jpg
A42: 37 | B42: Harina de Pistacho x 1kg | C42: Harina | E42: 13000 | F42: https://www.ferwer.es/img/blog/pistaciova-mouka-orechy-miska-lzice.webp
A43: =A41+1 -> 37 | B43: Harina de almendras con piel- OFERTA x 1Kg | C43: Harinas | E43: 4300 | F43: https://cdn.newgarden.com.ar/media/catalog/product/cache/dda7253a1a2f6711745de410175d10f8/h/a/harina_de_almendra_con_piel_tostada_1.jpg
A44: =A43+1 -> 38 | B44: Harina de almendras sin piel- OFERTA x 1Kg | C44: Harinas | E44: 4600 | F44: https://cdn.newgarden.com.ar/media/catalog/product/cache/dda7253a1a2f6711745de410175d10f8/h/a/harina-de-almendra-x-500-g.jpg
A45: =A44+1 -> 39 | F45: https://encrypted-tbn0.gstatic.com/images?q=tbn:ANd9GcS92NrShEYV2IBs41t7l15AfemBMPh_CI9d7w&s
A46: =A45+1 -> 40 | F46: https://encrypted-tbn0.gstatic.com/images?q=tbn:ANd9GcRz1cncBxMQqZYULO9agfvjTF3iJkAm-0myFg&s
A47: =A46+1 -> 41 | B47: Fécula de mandioca x 5Kg | C47: Harinas | E47: 11000 | F47: https://miserdiet.com.ar/wp-content/uploads/2022/09/fecula-de-mandioca.webp
A48: =A47+1 -> 42 | B48: Harina de arroz x 5Kg | C48: Harinas | E48: 7500 | F48: https://www.mayoristadelegumbres.com.ar/wp-content/uploads/2020/05/harina-de-arroz.jpg
A49: =A48+1 -> 43 | B49: Harina de algarroba x 1Kg MAYANA SIN TACC | C49: Harinas | E49: 7000 | F49: https://tienda.distribuidoraelcriollo.com/productos/2173.jpg
A50: =A49+1 -> 44 | B50: Kalena Roja Elaborada con palo | C50: Yerbas | E50: 4200 | F50: https://acdn-us.mitiendanube.com/stores/001/172/573/products/yerba-mate-kalena1-3211f4e93042469e3d15904280252761-1024-1024.webp
A51: =A50+1 -> 45 | B51: Kalena Celeste Elaborada sin palo | C51: Yerbas | E51: 5000 | F51: https://cdn.newgarden.com.ar/media/catalog/product/cache/dda7253a1a2f6711745de410175d10f8/y/e/yerba-mate-despalada-suave-kalena-500-g-sin-tacc.jpg
A52: =A51+1 -> 46 | B52: YERBA ROAPIPO SUAVE / TRADICIONAL 500gr Unidad | C52: Yerbas | E52: 3400 | F52: https://cdn.newgarden.com.ar/media/catalog/product/cache/dda7253a1a2f6711745de410175d10f8/y/e/yerba-organica-suave-roapipo-x-500-g.jpg
A53: =A52+1 -> 47 | B53: YERBA ROAPIPO SUAVE / TRADICIONAL 1 kgUnidad | C53: Yerbas | E53: 6500 | F53: https://cdn.newgarden.com.ar/media/catalog/product/cache/dda7253a1a2f6711745de410175d10f8/y/e/yerba-organica-suave-roapipo-1-kg.jpg
A54: 45 | B54: JESPER TRADICIONAL (ROJA) | C54: Yerbas | D54: POR UNIDAD | F54: https://d3ugyf2ht6aenh.cloudfront.net/stores/001/176/840/products/ym-jesper-tradicional-500gr-001-20da9d30e275ad318216523771807996-640-0.webp
A55: 46 | B55: JESPER ORGÁNICA (AMARILLA) | C55: Yerbas | E55: 4000 | F55: https://tse4.mm.bing.net/th?id=OIP.DTRt-dXsSsTT1lBhpLPZ7gHaHa&pid=Api&P=0&h=180
A56: 47 | B56: JESPER YERBA MATE CON HIERBAS (VERDE) | C56: Yerbas | F56: https://d2r9epyceweg5n.cloudfront.net/stores/001/705/896/products/yerba-mate-jesper-compuesta-con-te-verde-500g1-9a6e26f805a98132a616231549794860-640-0.jpg
A57: 48 | B57: LEGADO ORGANICA | C57: Yerbas | E57: 3000 | F57: https://tse4.mm.bing.net/th?id=OIP.n9-T2Os4RPn8oLluV2nFpAAAAA&pid=Api&P=0&h=180
B58: Fibra Lasfor x 1kg | C58: Cereal | E58: 6500
A59: 49 | B59: Mermelada Los Carolinos Ciruela/Naranja/Zapallo/Durazno/Tomate/Higo | C59: Mermeladas | E59: 3100 | F59: https://http2.mlstatic.com/D_NQ_NP_2X_919861-MLA72618726265_112023-F.webp
A60: =A59+1 -> 50 | B60: Mermelada Frutilla/Frutos Rojos/Arandanos | C60: Mermeladas | E60: 3500 | F60: https://d22fxaf9t8d39k.cloudfront.net/cca33aafd7869cbe5ba0a2754ceb3c95195abdfd4c3f12773805881517bb6c3732002.webp
B61: Mermelada La Tranquilina Arándano Light | C61: Mermeladas | E61: 5500 | F61: https://latranquilina.com/wp-content/uploads/2025/07/Arandano-sin-azucar-300x300.png
B62: Mermelada La Tranquilina Ciruela Light | C62: Mermeladas | E62: 4500 | F62: https://latranquilina.com/wp-content/uploads/2025/07/Ciruela-sin-azucar-300x300.png
B63: Mermelada La Tranquilina Durazno Light | C63: Mermeladas | E63: 5500 | F63: https://latranquilina.com/wp-content/uploads/2025/07/Durazno-sin-azucar-300x300.png
B64: Mermelada La Tranquilina Frambuesa Light | C64: Mermeladas | E64: 6000 | F64: https://latranquilina.com/wp-content/uploads/2025/07/Frambuesa-sin-azucar-300x300.png
B65: Mermelada La Tranquilina Frutilla Light | C65: Mermeladas | E65: 5500 | F65: https://latranquilina.com/wp-content/uploads/2025/07/Frutilla-sin-azucar-300x300.png
B66: Mermelada La Tranquilina Frutos del Bosque Light | C66: Mermeladas | E66: 5500 | F66: https://latranquilina.com/wp-content/uploads/2025/07/Frutos-del-bosque-sin-azucar-300x300.png
B67: Mermelada La Tranquilina Higo Light | C67: Mermeladas | E67: 4500 | F67: https://latranquilina.com/wp-content/uploads/2025/08/higos-sin-azucar-300x300.png
B68: Mermelada La Tranquilina Citricos (Limón, pomelo, naranja) light | C68: Mermeladas | E68: 4500 | F68: https://latranquilina.com/wp-content/uploads/2025/07/3-Citricos-sin-azucar-300x300.png
B69: Mermelada La Tranquilina Manzana Light | C69: Mermeladas | E69: 4500 | F69: https://latranquilina.com/wp-content/uploads/2025/07/manzana-lightDSC_4420-300x300.png
B70: Mermelada La Tranquilina Pera Light | C70: Mermelada | E70: 4500 | F70: https://latranquilina.com/wp-content/uploads/2025/07/pera-lightDSC_4433-300x300.png
B71: Mermelada La Tranquilina Membrillo Light | C71: Mermelada | E71: 5500 | F71: https://latranquilina.com/wp-content/uploads/2025/08/membrillo-300x300.png
B72: Mermelada La Tranquilina Naranja Light | C72: Mermelada | E72: 4500 | F72: https://latranquilina.com/wp-content/uploads/2025/07/naranja-lightDSC_4435-300x300.png
... B76: Mermelada La Tranquilina Rosa Mosqueta Light | C76: Mermelada | E76: 5500 | F76: https://latranquilina.com/wp-content/uploads/2025/07/rosa-mosqueta-lightDSC_4413-300x300.png
A77: 51 | B77: Miel Aldeva. Envase vidrio | C77: Miel | E77: 3500 | F77: https://frutosare.com.ar/wp-content/uploads/2017/03/miel-pura-aldeva.jpg
A78: 52 | B78: Miel Pura Nani Multifloral 1kg | C78: Miel | E78: 5000 | F78: https://encrypted-tbn0.gstatic.com/images?q=tbn:ANd9GcSpI_ERyqOCsluKvGWWjXtp3XNCv-EEQuzVMw&s
A79: =A78+1 -> 53 | B79: Miel Pura Nani Multifloral 500g | C79: Miel | E79: 3500 | F79: https://encrypted-tbn0.gstatic.com/images?q=tbn:ANd9GcSpI_ERyqOCsluKvGWWjXtp3XNCv-EEQuzVMw&s
A80: 54 | B80: Miel Entrenut. Envase Vidrio. Líquida o Cremosa | C80: Miel | E80: 5000 | F80: https://acdn-us.mitiendanube.com/stores/801/315/products/dsc097931-39090b0594f74fbc3a16580093471790-1024-1024.webp
A81: 55 | B81: Pasta de Mani Entrenuts Natural/Crocante | C81: Pasta de Mani | E81: 2600 | F81: https://encrypted-tbn0.gstatic.com/images?q=tbn:ANd9GcRY810Vt2WyDg5IFqNq80e2pXb7ez55V5mcIw&s
B82: Pasta de Mani Entrenuts Proteica Cookies & cream/ Salted Caramel | C82: Pasta de Mani | E82: 3600 | F82: https://distribuidorafresh.com.ar/wp-content/uploads/2024/04/pasta-mani-salted-caramel-protein.webp
A83: =A81+1 -> 56 | B83: Aceite de Oliva Sol Cuyano 500ml | C83: Aceites | E83: 11000 | F83: https://encrypted-tbn0.gstatic.com/images?q=tbn:ANd9GcSP8l0GvNsOPizBdbH2eDO_VNKcQN1PUixOEA&s
B84: Aceite de Oliva Extra Virgen Blend x 900cc | C84: Aceites | E84: 12000
A85: 57 | B85: Aceite de Coco Entrenuts x 1000cc Neutro | C85: Aceites | E85: 16000 | F85: https://http2.mlstatic.com/D_NQ_NP_2X_780003-MLA88118277989_072025-F.webp
A86: 58 | B86: Aceite de Coco Entrenuts x 500cc Neutro | C86: Aceites | E86: 8300 | F86: https://acdn-us.mitiendanube.com/stores/002/268/228/products/aceite-de-coco-neutro-entrenuts-500cc-vegano-libre-de-gluten-f15c97bb5bb04681f517477570471289-1024-1024.png
A87: 59 | B87: Aceite de Coco Entrenuts x 360cc Neutro | C87: Aceites | E87: 5800 | F87: https://warneke.com.ar/wp-content/uploads/2023/05/aceitecoco-600x601.png
A88: =A87+1 -> 60 | B88: Aceite de Coco Entrenuts x 360cc Virgen | C88: Aceites | E88: 10000 | F88: https://acdn-us.mitiendanube.com/stores/001/326/060/products/aceite-de-coco-virgen-organico-entrenuts-sin-tacc-360g1-665c91f99d43c6b6e916760505815272-1024-1024.jpg
A89: =A88+1 -> 61 | B89: Aceite de Coco Entrenuts x 200cc Neutro | C89: Aceites | E89: 4000 | F89: https://http2.mlstatic.com/D_NQ_NP_934251-MLA76635794822_062024-O.webp
A90: =A89+1 -> 62 | B90: Aceite de Coco Entrenuts x 200cc Virgen | C90: Aceites | E90: 6200 | F90: https://laduvalina.com.ar/wp-content/uploads/2023/03/ACCCC.webp
A91: 63 | B91: Aceite de Coco MCT Trigliceridos de cadena media 250cc | C91: Aceites | E91: 12000 | F91: https://greenco.com.ar/Content/images/articulos/ENTR28_1.jpg
A92: 62 | B92: Aceite CBD MEDICINAL ROYAL 10ML al 39,99% | C92: Aceites | E92: 21000 | F92: https://d2j6dbq0eux0bg.cloudfront.net/images/24120122/2384747864.jpg
B93: Vinagre Sidra de Manzana Organico 250cm3 | C93: Viangre | E93: 6300 | F93: https://acdn.mitiendanube.com/stores/750/800/products/vinagre-de-manzana-organico-pampa-gourmet-250ml-templeorganico1-097a17c1cbb6addb8516613479371104-640-0.png
A94: 63 | B94: Manteca clarificada Ghee Entrenetus | C94: Ghee | E94: 10000 | F94: https://http2.mlstatic.com/D_NQ_NP_756527-MLA49314673527_032022-O.webp
A95: =A94+1 -> 64 | B95: Aceite de Orégano Gotas | C95: Aceites | E95: 5500 | F95: https://d22fxaf9t8d39k.cloudfront.net/3ac5d3be0ea9578415b1cade887e338f6d2384b9ccaf5ecf8c8d54cfee8164c180985.jpeg
A96: =A95+1 -> 65 | B96: Almendras con chocolate 1kg Los Carolinos | C96: Confituras | E96: 32500 | F96: https://cdn.newgarden.com.ar/media/catalog/product/cache/dda7253a1a2f6711745de410175d10f8/a/l/almendra-con-chocolate-con-leche_1.jpg
A97: =A96+1 -> 66 | B97: Maní con Chocolate 1kg Los Carolinos | C97: Confituras | E97: 18000 | F97: https://cdn.newgarden.com.ar/media/catalog/product/cache/dda7253a1a2f6711745de410175d10f8/m/a/mani-con-chocolate-1kg.jpg
A98: =A97+1 -> 67 | B98: Pasas con Chocolate 1kg Los Carolinos | C98: Confituras | E98: 20000 | F98: https://cdn.newgarden.com.ar/media/catalog/product/cache/dda7253a1a2f6711745de410175d10f8/p/a/pasas-de-uva-con-chocolate_1_1.jpg
A99: =A98+1 -> 68 | B99: Cereal Cubierto con Chocolate 1kg Los Carolinos | C99: Confituras | E99: 19300 | F99: https://encrypted-tbn0.gstatic.com/images?q=tbn:ANd9GcSz2ZM94uX4DUx4vnTwdHp2COhpobgXxMIeLA&s
B100: Garrapiñadas de mani AVILA 1kg | C100: Confituras | E100: 6500 | F100: https://tse1.mm.bing.net/th/id/OIP.eo1rusvZ54XxX90yna76NQHaH0?pid=Api&P=0&h=180
B101: Garrapiñadas de almendras 500gr | C101: Confituras | E101: 11000
A102: =A99+1 -> 69 | B102: Chip de Chocolate semiamargo 1kg Alpino | C102: Confituras | E102: 11000 | F102: https://acdn-us.mitiendanube.com/stores/004/033/662/products/imagen-de-whatsapp-2024-08-01-a-las-07-36-03_d8839284-5163b50b9fb09dd33317225085844010-1024-1024.webp
A103: 70 | B103: Chip de Chocolate blanco 1kg Alpino | C103: Confituras | E103: 11000 | F103: https://acdn-us.mitiendanube.com/stores/004/033/662/products/imagen-de-whatsapp-2024-08-01-a-las-08-08-36_308dd65b-4e6c33c9d98bc5636c17225105334782-1024-1024.webp
...

Sheet ref
A1: https://newgarden.com.ar/

Sheet pedido distribuidora
A2: 1 | B2: Mix Premiun gourmet | C2: 6 kg | D2: 15500 | E2: =D2*6 -> 93000
A3: 3 | B3: Quinoa | C3: 1kg | D3: 6000 | E3: =D3 -> 6000
A4: 4 | B4: Mani Tostado sin sal | C4: 1kg | D4: 2500 | E4: =D4 -> 2500
A5: 2 | B5: Mix Criollo o runner con banan | C5: 2kg | D5: 6600 | E5: =D5*2 -> 13200
A6: 6 | B6: Harina de Almendras sin piel | C6: 2kg | D6: 3600 | E6: =D6*2 -> 7200
A7: 18 | B7: Mermelada Los Carolinos Durazno | C7: 1 | D7: 2220 | E7: =D7 -> 2220
A8: 8 | B8: Nuez Mariposa | C8: 1kg | D8: 17900 | E8: =D8 -> 17900
A9: 5 | B9: Mani Tostado con sal | C9: 3kg | D9: 2500 | E9: =D9*3 -> 7500
A10: 9 | B10: Pistachos con cascara | C10: 2kg | D10: 28500 | E10: =D10*2 -> 57000
A11: 7 | B11: Harina de Almendras con piel | C11: 2kg | D11: 3400 | E11: =D11*2 -> 6800
A12: 10 | B12: Bananas disecadas | C12: 1kg | D12: 6400 | E12: =D12 -> 6400
A13: 11 | B13: Harina de coco | C13: 2kg | D13: 4600 | E13: =D13*2 -> 9200
A14: 12 | B14: Aceite de coco neutro x 360 | C14: 1 | D14: 3300 | E14: =D14 -> 3300
A15: 13 | B15: Chip chocolate | C15: 1kg | D15: 6600 | E15: =D15 -> 6600
A16: 14 | B16: Galletitas Nutresan sabor coco | C16: 1 | D16: 1130 | E16: =D16 -> 1130
A17: 15 | B17: Galletitas Nutresan sabor algarroba | C17: 1 | D17: 1140 | E17: =D17 -> 1140
B18: castañas caju | C18: 1kg | D18: 12300 | E18: =D18 -> 12300
B19: arandanos | C19: 4kg | D19: 7900 | E19: =D19*4 -> 31600
A20: 16 | B20: mix semillas | C20: 1kg | D20: 2600 | E20: =D20 -> 2600
B21: pasas con chocolate | C21: 1kg | D21: 11000 | E21: =D21 -> 11000
A22: 17 | B22: castañas para | C22: 1kg | D22: 16800 | E22: =D22 -> 16800
A23: 19 | B23: nueces pecan | C23: 1kg | D23: 17100 | E23: =1 -> 1
E24: =SUM(E2:E23) -> 315391

Sheet Clientes
A1: id | B1: cliente
A2: 1 | B2: Cecilia (Lauti)
A3: =A2+1 -> 2 | B3: Marianela (Laure)
A4: =A3+1 -> 3 | B4: Marcela Rivera
A5: =A4+1 -> 4 | B5: Rosario
A6: =A5+1 -> 5 | B6: Saha
A7: =A6+1 -> 6 | B7: Raul
A8: =A7+1 -> 7 | B8: Gustavo
A9: =A8+1 -> 8 | B9: Gabi
A10: =A9+1 -> 9 | B10: Luciano
A11: =A10+1 -> 10 | B11: Auri
A12: =A11+1 -> 11 | B12: Maiju
A13: =A12+1 -> 12 | B13: Luz
A14: =A13+1 -> 13 | B14: Gla
... A37: =A36+1 -> 36 | B37: Marina Moriconi
A38: 37 | B38: Laura Area 10
A39: 38 | B39: Dora area 2
A40: 39 | B40: Juan pablo (vallese)
A41: 40 | B41: Pao Migliaro
A42: 41 | B42: Gisella area 13
A43: 42 | B43: Candela
A44: 43 | B44: Cecilia
A45: 44 | B45: Florencia Cardozzo
A46: 45 | B46: Ursula Area 11
A47: 46 | B47: Silvia
A48: 47 | B48: Iris Area 10 Lote 171
A49: 48 | B49: Lucia Area 9 Lote 229
... A56: 55 | B56: Fernando Messina Area 11

Sheet Pedidos_JA
A1: Semana | B1: Producto | C1: Costo | D1: Precio Unitario | E1: Existe Un Pedido | F1: Laura Area 10 | G1: Vale | H1: Suegra Cuñada Nori | I1: Pato | J1: Aldana Area 2 | K1: Mariana Area 7 Lote 253 | L1: Marina Moriconi | M1: Constanza Area 1 | N1: Adriana Davi A. 1 L. 222 | O1: Paola Area 10 Lote 360 | P1: Marta | Q1: Nati Conde | R1: Nati Cuñada Nori | S1: cliente | T1: cliente | U1: cliente | V1: cliente | W1: cliente | X1: cliente | Y1: cliente | Z1: cliente | AA1: cliente | AB1: TOTAL
A2: =WEEKNUM(TODAY()) -> 17 | B2: =catalog!B2 -> Nuez Mariposa Extra Light x 1 Kg | D2: =catalog!E2 -> 20500 | E2: =IF(sum(F2:AA2)>=1,"SI", "NO") -> SI | P2: 2 | AB2: =sum(F2:AA2) -> 2
A3: =WEEKNUM(TODAY()) -> 17 | B3: =catalog!B3 -> Almendra Non Pareil 27/30 x 1 Kg | D3: =catalog!E3 -> 23000 | E3: =IF(sum(F3:AA3)>=1,"SI", "NO") -> SI | J3: 1 | K3: 1 | AB3: =sum(F3:AA3) -> 2
A4: =WEEKNUM(TODAY()) -> 17 | B4: =catalog!B4 -> Mani tostado con y sin sal PREMIUM x 1 Kg | D4: =catalog!E4 -> 3000 | E4: =IF(sum(F4:AA4)>=1,"SI", "NO") -> SI | N4: 1 | P4: 1 | R4: 1 | AB4: =sum(F4:AA4) -> 3
A5: =WEEKNUM(TODAY()) -> 17 | B5: =#REF! -> #REF! | D5: =#REF! -> #REF! | E5: =IF(sum(F5:AA5)>=1,"SI", "NO") -> SI | J5: 1 | AB5: =sum(F5:AA5) -> 1
A6: =WEEKNUM(TODAY()) -> 17 | B6: =catalog!B5 -> Nuez Pecan x 1 Kg | D6: =catalog!E5 -> 34600 | E6: =IF(sum(F6:AA6)>=1,"SI", "NO") -> NO | AB6: =sum(F6:AA6) -> 0
A7: =WEEKNUM(TODAY()) -> 17 | B7: =catalog!B6 -> Cajú W4 brasilero x 1 Kg | D7: =catalog!E6 -> 19500 | E7: =IF(sum(F7:AA7)>=1,"SI", "NO") -> SI | P7: 2 | R7: 1 | AB7: =sum(F7:AA7) -> 3
A8: =WEEKNUM(TODAY()) -> 17 | B8: =catalog!B8 -> Castañas de PARA x 1 Kg | D8: =catalog!E8 -> 40200 | E8: =IF(sum(F8:AA8)>=1,"SI", "NO") -> SI | R8: 1 | AB8: =sum(F8:AA8) -> 1
A9: =WEEKNUM(TODAY()) -> 17 | B9: =catalog!B9 -> Avellanas grandes x 1 Kg | D9: =catalog!E9 -> 33200 | E9: =IF(sum(F9:AA9)>=1,"SI", "NO") -> NO | AB9: =sum(F9:AA9) -> 0
A10: =WEEKNUM(TODAY()) -> 17 | B10: =#REF! -> #REF! | D10: =#REF! -> #REF! | E10: =IF(sum(F10:AA10)>=1,"SI", "NO") -> NO | AB10: =sum(F10:AA10) -> 0
A11: =WEEKNUM(TODAY()) -> 17 | B11: =catalog!B10 -> Pasas Rubia 1kg | D11: =catalog!E10 -> 8200 | E11: =IF(sum(F11:AA11)>=1,"SI", "NO") -> NO | AB11: =sum(F11:AA11) -> 0
A12: =WEEKNUM(TODAY()) -> 17 | B12: =catalog!B11 -> Pistacho salado con cascara x 1 Kg | D12: =catalog!E11 -> 41000 | E12: =IF(sum(F12:AA12)>=1,"SI", "NO") -> NO | AB12: =sum(F12:AA12) -> 0
A13: =WEEKNUM(TODAY()) -> 17 | B13: =catalog!B13 -> Mix criollo o Runner (Nuez cuartos , almendra, cajú, mani, pasas rubias y morochas) x 1kg | D13: =catalog!E13 -> 8200 | E13: =IF(sum(F13:AA13)>=1,"SI", "NO") -> SI | H13: 1 | AB13: =sum(F13:AA13) -> 1
A14: =WEEKNUM(TODAY()) -> 17 | B14: =catalog!B15 -> Mix premium gourmet (Cajú, almendras, nueces y avellanas) x 1kg | D14: =catalog!E15 -> 23000 | E14: =IF(sum(F14:AA14)>=1,"SI", "NO") -> SI | G14: 1 | L14: 1 | P14: 3 | AB14: =sum(F14:AA14) -> 5
A15: =WEEKNUM(TODAY()) -> 17 | B15: =catalog!B17 -> Mix criollo o runner con bananitas (Cajú, almendras, nueces, mani, pasas rubias y morochas, bananitas) | D15: =catalog!E17 -> 8400 | E15: =IF(sum(F15:AA15)>=1,"SI", "NO") -> SI | I15: 1 | Q15: 1 | AB15: =sum(F15:AA15) -> 2
A16: =WEEKNUM(TODAY()) -> 17 | B16: =catalog!B18 -> Mix cervecero (semillas peladas de girasol y de zapallo, castañas de cajú saladas, maní salado, maní japonés) 1kg | D16: =catalog!E18 -> 6300 | E16: =IF(sum(F16:AA16)>=1,"SI", "NO") -> SI | H16: 1 | AB16: =sum(F16:AA16) -> 1
A17: =WEEKNUM(TODAY()) -> 17 | B17: =catalog!B21 -> Bananas disecadas x 1kg | D17: =catalog!E21 -> 12000 | E17: =IF(sum(F17:AA17)>=1,"SI", "NO") -> NO | AB17: =sum(F17:AA17) -> 0
A18: =WEEKNUM(TODAY()) -> 17 | B18: =catalog!B22 -> Damasco turco grande x 1kg | D18: =catalog!E22 -> 42000 | E18: =IF(sum(F18:AA18)>=1,"SI", "NO") -> NO | AB18: =sum(F18:AA18) -> 0
A19: =WEEKNUM(TODAY()) -> 17 | B19: =catalog!B23 -> Tomates deshidratados x 1kg | D19: =catalog!E23 -> 15600 | E19: =IF(sum(F19:AA19)>=1,"SI", "NO") -> NO | AB19: =sum(F19:AA19) -> 0
A20: =WEEKNUM(TODAY()) -> 17 | B20: =catalog!B26 -> Ciruelas d Agen sin carozo x 1kg | D20: =catalog!E26 -> 7500 | E20: =IF(sum(F20:AA20)>=1,"SI", "NO") -> SI | P20: 1 | AB20: =sum(F20:AA20) -> 1
A21: =WEEKNUM(TODAY()) -> 17 | B21: =catalog!B27 -> Arandanos | D21: =catalog!E27 -> 13500 | E21: =IF(sum(F21:AA21)>=1,"SI", "NO") -> SI | F21: 2 | P21: 1 | AB21: =sum(F21:AA21) -> 3
A22: =WEEKNUM(TODAY()) -> 17 | B22: =catalog!B28 -> Higos negros x 5kg | D22: =catalog!E28 -> 47000 | E22: =IF(sum(F22:AA22)>=1,"SI", "NO") -> NO | AB22: =sum(F22:AA22) -> 0
A23: =WEEKNUM(TODAY()) -> 17 | B23: =catalog!B29 -> Datiles Egipto Caja 1 kg OFERTA | D23: =catalog!E29 -> 8000 | E23: =IF(sum(F23:AA23)>=1,"SI", "NO") -> SI | M23: 0.5 | R23: 0.5 | AB23: =sum(F23:AA23) -> 1
A24: =WEEKNUM(TODAY()) -> 17 | B24: =#REF! -> #REF! | D24: =#REF! -> #REF! | E24: =IF(sum(F24:AA24)>=1,"SI", "NO") -> NO | AB24: =sum(F24:AA24) -> 0
A25: =WEEKNUM(TODAY()) -> 17 | B25: =catalog!B31 -> Mix de semillas (Lino, girasol, sésamo) x 1kg | D25: =catalog!E31 -> 4000 | E25: =IF(sum(F25:AA25)>=1,"SI", "NO") -> SI | I25: 1 | Q25: 1 | R25: 1 | AB25: =sum(F25:AA25) -> 3
A26: =WEEKNUM(TODAY()) -> 17 | B26: =catalog!B32 -> Lino x 1Kg | D26: =catalog!E32 -> 3300 | E26: =IF(sum(F26:AA26)>=1,"SI", "NO") -> NO | AB26: =sum(F26:AA26) -> 0
A27: =WEEKNUM(TODAY()) -> 17 | B27: =catalog!B33 -> Chia premium x 1Kg | D27: =catalog!E33 -> 8700 | E27: =IF(sum(F27:AA27)>=1,"SI", "NO") -> NO | AB27: =sum(F27:AA27) -> 0
A28: =WEEKNUM(TODAY()) -> 17 | B28: =catalog!B34 -> Sésamo integral x 1Kg | D28: =catalog!E34 -> 5800 | E28: =IF(sum(F28:AA28)>=1,"SI", "NO") -> NO | AB28: =sum(F28:AA28) -> 0
A29: =WEEKNUM(TODAY()) -> 17 | B29: =catalog!B35 -> Sesamo blanco x 1Kg | D29: =catalog!E35 -> 10000 | E29: =IF(sum(F29:AA29)>=1,"SI", "NO") -> NO | AB29: =sum(F29:AA29) -> 0
A30: =WEEKNUM(TODAY()) -> 17 | B30: =catalog!B36 -> Girasol x 1Kg | D30: =catalog!E36 -> 4100 | E30: =IF(sum(F30:AA30)>=1,"SI", "NO") -> SI | P30: 2 | AB30: =sum(F30:AA30) -> 2
A31: =WEEKNUM(TODAY()) -> 17 | B31: =catalog!B37 -> Quinoa x 1Kg | D31: =catalog!E37 -> 12400 | E31: =IF(sum(F31:AA31)>=1,"SI", "NO") -> SI | F31: 1 | AB31: =sum(F31:AA31) -> 1
A32: =WEEKNUM(TODAY()) -> 17 | B32: =catalog!B38 -> Zapallo x 1Kg | D32: =catalog!E38 -> 14000 | E32: =IF(sum(F32:AA32)>=1,"SI", "NO") -> SI | P32: 1 | AB32: =sum(F32:AA32) -> 1
A33: =WEEKNUM(TODAY()) -> 17 | B33: =catalog!B40 | D33: =catalog!E40 | E33: =IF(sum(F33:AA33)>=1,"SI", "NO") -> NO | AB33: =sum(F33:AA33) -> 0
A34: =WEEKNUM(TODAY()) -> 17 | B34: =catalog!B41 -> Harina de coco x 1Kg | D34: =catalog!E41 -> 5800 | E34: =IF(sum(F34:AA34)>=1,"SI", "NO") -> SI | F34: 2 | O34: 1 | AB34: =sum(F34:AA34) -> 3
A35: =WEEKNUM(TODAY()) -> 17 | B35: =catalog!B43 -> Harina de almendras con piel- OFERTA x 1Kg | D35: =catalog!E43 -> 4300 | E35: =IF(sum(F35:AA35)>=1,"SI", "NO") -> SI | H35: 1 | AB35: =sum(F35:AA35) -> 1
A36: =WEEKNUM(TODAY()) -> 17 | B36: =catalog!B44 -> Harina de almendras sin piel- OFERTA x 1Kg | D36: =catalog!E44 -> 4600 | E36: =IF(sum(F36:AA36)>=1,"SI", "NO") -> SI | O36: 2 | Q36: 1 | AB36: =sum(F36:AA36) -> 3
A37: =WEEKNUM(TODAY()) -> 17 | B37: =catalog!B45 | D37: =catalog!E45 | E37: =IF(sum(F37:AA37)>=1,"SI", "NO") -> NO | AB37: =sum(F37:AA37) -> 0
A38: =WEEKNUM(TODAY()) -> 17 | B38: =catalog!B46 | D38: =catalog!E46 | E38: =IF(sum(F38:AA38)>=1,"SI", "NO") -> NO | AB38: =sum(F38:AA38) -> 0
A39: =WEEKNUM(TODAY()) -> 17 | B39: =catalog!B47 -> Fécula de mandioca x 5Kg | D39: =catalog!E47 -> 11000 | E39: =IF(sum(F39:AA39)>=1,"SI", "NO") -> NO | AB39: =sum(F39:AA39) -> 0
A40: =WEEKNUM(TODAY()) -> 17 | B40: =catalog!B48 -> Harina de arroz x 5Kg | D40: =catalog!E48 -> 7500 | E40: =IF(sum(F40:AA40)>=1,"SI", "NO") -> NO | AB40: =sum(F40:AA40) -> 0
A41: =WEEKNUM(TODAY()) -> 17 | B41: =catalog!B49 -> Harina de algarroba x 1Kg MAYANA SIN TACC | D41: =catalog!E49 -> 7000 | E41: =IF(sum(F41:AA41)>=1,"SI", "NO") -> SI | O41: 1 | AB41: =sum(F41:AA41) -> 1
A42: =WEEKNUM(TODAY()) -> 17 | B42: =#REF! -> #REF! | D42: =#REF! -> #REF! | E42: =IF(sum(F42:AA42)>=1,"SI", "NO") -> NO | AB42: =sum(F42:AA42) -> 0
A43: =WEEKNUM(TODAY()) -> 17 | B43: =catalog!B50 -> Kalena Roja Elaborada con palo | D43: =catalog!E50 -> 4200 | E43: =IF(sum(F43:AA43)>=1,"SI", "NO") -> NO | AB43: =sum(F43:AA43) -> 0
A44: =WEEKNUM(TODAY()) -> 17 | B44: =catalog!B51 -> Kalena Celeste Elaborada sin palo | D44: =catalog!E51 -> 5000 | E44: =IF(sum(F44:AA44)>=1,"SI", "NO") -> SI | R44: 2 | AB44: =sum(F44:AA44) -> 2
A45: =WEEKNUM(TODAY()) -> 17 | B45: =catalog!B52 -> YERBA ROAPIPO SUAVE / TRADICIONAL 500gr Unidad | D45: =catalog!E52 -> 3400 | E45: =IF(sum(F45:AA45)>=1,"SI", "NO") -> NO | AB45: =sum(F45:AA45) -> 0
A46: =WEEKNUM(TODAY()) -> 17 | B46: =catalog!B53 -> YERBA ROAPIPO SUAVE / TRADICIONAL 1 kgUnidad | D46: =catalog!E53 -> 6500 | E46: =IF(sum(F46:AA46)>=1,"SI", "NO") -> SI | F46: 1 | AB46: =sum(F46:AA46) -> 1
A47: =WEEKNUM(TODAY()) -> 17 | B47: =catalog!B59 -> Mermelada Los Carolinos Ciruela/Naranja/Zapallo/Durazno/Tomate/Higo | D47: =catalog!E59 -> 3100 | E47: =IF(sum(F47:AA47)>=1,"SI", "NO") -> NO | AB47: =sum(F47:AA47) -> 0
A48: =WEEKNUM(TODAY()) -> 17 | B48: =catalog!B60 -> Mermelada Frutilla/Frutos Rojos/Arandanos | D48: =catalog!E60 -> 3500 | E48: =IF(sum(F48:AA48)>=1,"SI", "NO") -> NO | AB48: =sum(F48:AA48) -> 0
A49: =WEEKNUM(TODAY()) -> 17 | B49: =catalog!B81 -> Pasta de Mani Entrenuts Natural/Crocante | D49: =catalog!E81 -> 2600 | E49: =IF(sum(F49:AA49)>=1,"SI", "NO") -> NO | AB49: =sum(F49:AA49) -> 0
A50: =WEEKNUM(TODAY()) -> 17 | B50: =catalog!B83 -> Aceite de Oliva Sol Cuyano 500ml | D50: =catalog!E83 -> 11000 | E50: =IF(sum(F50:AA50)>=1,"SI", "NO") -> NO | AB50: =sum(F50:AA50) -> 0
A51: =WEEKNUM(TODAY()) -> 17 | B51: =catalog!B87 -> Aceite de Coco Entrenuts x 360cc Neutro | D51: =catalog!E87 -> 5800 | E51: =IF(sum(F51:AA51)>=1,"SI", "NO") -> SI | I51: 1 | AB51: =sum(F51:AA51) -> 1
A52: =WEEKNUM(TODAY()) -> 17 | B52: =catalog!B88 -> Aceite de Coco Entrenuts x 360cc Virgen | D52: =catalog!E88 -> 10000 | E52: =IF(sum(F52:AA52)>=1,"SI", "NO") -> NO | AB52: =sum(F52:AA52) -> 0
A53: =WEEKNUM(TODAY()) -> 17 | B53: =catalog!B89 -> Aceite de Coco Entrenuts x 200cc Neutro | D53: =catalog!E89 -> 4000 | E53: =IF(sum(F53:AA53)>=1,"SI", "NO") -> SI | N53: 1 | AB53: =sum(F53:AA53) -> 1
A54: =WEEKNUM(TODAY()) -> 17 | B54: =catalog!B90 -> Aceite de Coco Entrenuts x 200cc Virgen | D54: =catalog!E90 -> 6200 | E54: =IF(sum(F54:AA54)>=1,"SI", "NO") -> NO | AB54: =sum(F54:AA54) -> 0
A55: =WEEKNUM(TODAY()) -> 17 | B55: =catalog!B94 -> Manteca clarificada Ghee Entrenetus | D55: =catalog!E94 -> 10000 | E55: =IF(sum(F55:AA55)>=1,"SI", "NO") -> NO | AB55: =sum(F55:AA55) -> 0
A56: =WEEKNUM(TODAY()) -> 17 | B56: =catalog!B95 -> Aceite de Orégano Gotas | D56: =catalog!E95 -> 5500 | E56: =IF(sum(F56:AA56)>=1,"SI", "NO") -> SI | I56: 1 | AB56: =sum(F56:AA56) -> 1
A57: =WEEKNUM(TODAY()) -> 17 | B57: =catalog!B96 -> Almendras con chocolate 1kg Los Carolinos | D57: =catalog!E96 -> 32500 | E57: =IF(sum(F57:AA57)>=1,"SI", "NO") -> NO | AB57: =sum(F57:AA57) -> 0
A58: =WEEKNUM(TODAY()) -> 17 | B58: =catalog!B97 -> Maní con Chocolate 1kg Los Carolinos | D58: =catalog!E97 -> 18000 | E58: =IF(sum(F58:AA58)>=1,"SI", "NO") -> NO | AB58: =sum(F58:AA58) -> 0
A59: =WEEKNUM(TODAY()) -> 17 | B59: =catalog!B98 -> Pasas con Chocolate 1kg Los Carolinos | D59: =catalog!E98 -> 20000 | E59: =IF(sum(F59:AA59)>=1,"SI", "NO") -> NO | AB59: =sum(F59:AA59) -> 0
A60: =WEEKNUM(TODAY()) -> 17 | B60: =catalog!B99 -> Cereal Cubierto con Chocolate 1kg Los Carolinos | D60: =catalog!E99 -> 19300 | E60: =IF(sum(F60:AA60)>=1,"SI", "NO") -> NO | AB60: =sum(F60:AA60) -> 0
A61: =WEEKNUM(TODAY()) -> 17 | B61: =catalog!B102 -> Chip de Chocolate semiamargo 1kg Alpino | D61: =catalog!E102 -> 11000 | E61: =IF(sum(F61:AA61)>=1,"SI", "NO") -> NO | AB61: =sum(F61:AA61) -> 0
A62: =WEEKNUM(TODAY()) -> 17 | B62: =catalog!B104 -> Rocklets ARCOR 1kg | D62: =catalog!E104 -> 18000 | E62: =IF(sum(F62:AA62)>=1,"SI", "NO") -> NO | AB62: =sum(F62:AA62) -> 0
A63: =WEEKNUM(TODAY()) -> 17 | B63: =catalog!B105 -> Coco rallado 1kg MEDIUM FAT | D63: =catalog!E105 -> 9300 | E63: =IF(sum(F63:AA63)>=1,"SI", "NO") -> SI | H63: 1 | AB63: =sum(F63:AA63) -> 1
A64: =WEEKNUM(TODAY()) -> 17 | B64: =catalog!B112 -> Cacao amargo MAYANA SINTAC 1kg | D64: =catalog!E112 -> 14000 | E64: =IF(sum(F64:AA64)>=1,"SI", "NO") -> SI | O64: 1 | AB64: =sum(F64:AA64) -> 1
A65: =WEEKNUM(TODAY()) -> 17 | B65: =catalog!B117 -> Chocolate Alpino Tabletas 500gr Baño de Molde Semiamargo/con leche/blanco | D65: =catalog!E117 -> 7200 | E65: =IF(sum(F65:AA65)>=1,"SI", "NO") -> NO | AB65: =sum(F65:AA65) -> 0
A66: =WEEKNUM(TODAY()) -> 17 | B66: =catalog!B121 -> Galletitas Nutresan 250gr. sabor Coco | D66: =catalog!E121 -> 1600 | E66: =IF(sum(F66:AA66)>=1,"SI", "NO") -> NO | AB66: =sum(F66:AA66) -> 0
A67: =WEEKNUM(TODAY()) -> 17 | B67: =catalog!B122 -> Galletitas Nutresan 250gr. sabor Natural con miel | D67: =catalog!E122 -> 1600 | E67: =IF(sum(F67:AA67)>=1,"SI", "NO") -> NO | AB67: =sum(F67:AA67) -> 0
A68: =WEEKNUM(TODAY()) -> 17 | B68: =catalog!B123 -> Galletitas Nutresan 250gr. sabor Avena | D68: =catalog!E123 -> 1400 | E68: =IF(sum(F68:AA68)>=1,"SI", "NO") -> NO | AB68: =sum(F68:AA68) -> 0
A69: =WEEKNUM(TODAY()) -> 17 | B69: =catalog!B124 -> Galletitas Nutresan 250gr. sabor Algarroba | D69: =catalog!E124 -> 1700 | E69: =IF(sum(F69:AA69)>=1,"SI", "NO") -> NO | AB69: =sum(F69:AA69) -> 0
A70: =WEEKNUM(TODAY()) -> 17 | B70: =catalog!B125 -> Galletitas Nutresan 250gr. dulce trigo Naranja Apto Diabéticos | D70: =catalog!E125 -> 2000 | E70: =IF(sum(F70:AA70)>=1,"SI", "NO") -> NO | AB70: =sum(F70:AA70) -> 0
A71: =WEEKNUM(TODAY()) -> 17 | B71: =catalog!B126 -> Galletitas Nutresan 250gr. dulce trigo LimónApto Diabéticos | D71: =catalog!E126 -> 2000 | E71: =IF(sum(F71:AA71)>=1,"SI", "NO") -> NO | AB71: =sum(F71:AA71) -> 0
A72: =WEEKNUM(TODAY()) -> 17 | B72: =catalog!B133 -> Mini Crackers 5 semillas | D72: =catalog!E133 -> 1200 | E72: =IF(sum(F72:AA72)>=1,"SI", "NO") -> NO | AB72: =sum(F72:AA72) -> 0
A73: =WEEKNUM(TODAY()) -> 17 | B73: =catalog!B134 -> Brownie de Algarroba light 12 unidades | D73: =catalog!E134 -> 18000 | E73: =IF(sum(F73:AA73)>=1,"SI", "NO") -> NO | AB73: =sum(F73:AA73) -> 0
A74: =WEEKNUM(TODAY()) -> 17 | B74: =catalog!B141 -> Brownie con avena y mascabo light 12 unidades | D74: =catalog!E141 -> 18000 | E74: =IF(sum(F74:AA74)>=1,"SI", "NO") -> NO | AB74: =sum(F74:AA74) -> 0
A75: =WEEKNUM(TODAY()) -> 17 | B75: =#REF! -> #REF! | D75: =#REF! -> #REF! | E75: =IF(sum(F75:AA75)>=1,"SI", "NO") -> NO | AB75: =sum(F75:AA75) -> 0
A76: =WEEKNUM(TODAY()) -> 17 | B76: =#REF! -> #REF! | D76: =#REF! -> #REF! | E76: =IF(sum(F76:AA76)>=1,"SI", "NO") -> NO | AB76: =sum(F76:AA76) -> 0
A77: =WEEKNUM(TODAY()) -> 17 | B77: =#REF! -> #REF! | D77: =#REF! -> #REF! | E77: =IF(sum(F77:AA77)>=1,"SI", "NO") -> NO | AB77: =sum(F77:AA77) -> 0
A78: =WEEKNUM(TODAY()) -> 17 | B78: =catalog!B145 -> Granolas Archimboldo Tropical 1kg | D78: =catalog!E145 -> 7200 | E78: =IF(sum(F78:AA78)>=1,"SI", "NO") -> SI | H78: 1 | AB78: =sum(F78:AA78) -> 1
A79: =WEEKNUM(TODAY()) -> 17 | B79: =catalog!B146 -> Granolas Archimboldo Premium crujiente 1kg | D79: =catalog!E146 -> 7500 | E79: =IF(sum(F79:AA79)>=1,"SI", "NO") -> NO | AB79: =sum(F79:AA79) -> 0
A80: =WEEKNUM(TODAY()) -> 17 | B80: =catalog!B147 -> Granolas Archimboldo crocante con manzana 1kg | D80: =catalog!E147 -> 7200 | E80: =IF(sum(F80:AA80)>=1,"SI", "NO") -> NO | AB80: =sum(F80:AA80) -> 0
A81: =WEEKNUM(TODAY()) -> 17 | B81: =catalog!B148 -> Granolas Archimboldo Natural 1kg | D81: =catalog!E148 -> 7200 | E81: =IF(sum(F81:AA81)>=1,"SI", "NO") -> NO | AB81: =sum(F81:AA81) -> 0
A82: =WEEKNUM(TODAY()) -> 17 | B82: =catalog!B149 -> Granolas Archimboldo Energética 1kg | D82: =catalog!E149 -> 7200 | E82: =IF(sum(F82:AA82)>=1,"SI", "NO") -> NO | AB82: =sum(F82:AA82) -> 0
A83: =WEEKNUM(TODAY()) -> 17 | B83: =catalog!B160 -> Calcio cubano x90gr (x unidad) | D83: =catalog!E160 -> 1000 | E83: =IF(sum(F83:AA83)>=1,"SI", "NO") -> NO | AB83: =sum(F83:AA83) -> 0
A84: =WEEKNUM(TODAY()) -> 17 | B84: =catalog!B161 -> Cartílago de Tiburon x 90 gr | D84: =catalog!E161 -> 1000 | E84: =IF(sum(F84:AA84)>=1,"SI", "NO") -> NO | AB84: =sum(F84:AA84) -> 0
A85: =WEEKNUM(TODAY()) -> 17 | B85: =catalog!B162 -> Moringa en Polvo x 90gr | D85: =catalog!E162 -> 1000 | E85: =IF(sum(F85:AA85)>=1,"SI", "NO") -> NO | AB85: =sum(F85:AA85) -> 0
A86: =WEEKNUM(TODAY()) -> 17 | B86: =catalog!B163 -> Spirulina en Polvo x 90gr | D86: =catalog!E163 -> 1000 | E86: =IF(sum(F86:AA86)>=1,"SI", "NO") -> NO | AB86: =sum(F86:AA86) -> 0
A87: =WEEKNUM(TODAY()) -> 17 | B87: =catalog!B164 -> Colageno en Polvo x 90gr | D87: =catalog!E164 -> 1000 | E87: =IF(sum(F87:AA87)>=1,"SI", "NO") -> NO | AB87: =sum(F87:AA87) -> 0
A88: =WEEKNUM(TODAY()) -> 17 | B88: =catalog!B165 -> Maca Kalpa 500gr | D88: =catalog!E165 -> 1700 | E88: =IF(sum(F88:AA88)>=1,"SI", "NO") -> NO | AB88: =sum(F88:AA88) -> 0
A89: =WEEKNUM(TODAY()) -> 17 | B89: =catalog!B166 -> Maca Negra Preimun x 100gr | D89: =catalog!E166 -> 1500 | E89: =IF(sum(F89:AA89)>=1,"SI", "NO") -> NO | AB89: =sum(F89:AA89) -> 0
A90: =WEEKNUM(TODAY()) -> 17 | B90: =catalog!B168 -> Te Matcha 50gr | D90: =catalog!E168 -> 3000 | E90: =IF(sum(F90:AA90)>=1,"SI", "NO") -> SI | I90: 1 | L90: 1 | AB90: =sum(F90:AA90) -> 2
A91: =WEEKNUM(TODAY()) -> 17 | B91: =catalog!B169 -> Sal de himalaya fina 1kg | D91: =catalog!E169 -> 3000 | E91: =IF(sum(F91:AA91)>=1,"SI", "NO") -> SI | Q91: 1 | AB91: =sum(F91:AA91) -> 1
A92: 15 | B92: TOTAL SEMANAL | E92: =IF(sum(F92:AA92)>=1,"SI", "NO") -> #REF! | F92: =SUMPRODUCT(F2:F91 , $D2:$D91) -> #REF! | G92: =SUMPRODUCT(G2:G91 , $D2:$D91) -> #REF! | H92: =SUMPRODUCT(H2:H91 , $D2:$D91) -> #REF! | I92: =SUMPRODUCT(I2:I91 , $D2:$D91) -> #REF! | J92: =SUMPRODUCT(J2:J91 , $D2:$D91) -> #REF! | K92: =SUMPRODUCT(K2:K91 , $D2:$D91) -> #REF! | L92: =SUMPRODUCT(L2:L91 , $D2:$D91) -> #REF! | M92: =SUMPRODUCT(M2:M91 , $D2:$D91) -> #REF! | ... R92: =SUMPRODUCT(R2:R91 , $D2:$D91) -> #REF! | AB92: =sum(F92:AA92) -> #REF!
B93: =catalog!B205 | D93: =catalog!E205 | AB93: =sum(F93:AA93) -> 0
A94: Semana | B94: Producto | C94: Costo | D94: Precio Unitario | E94: Existe Un Pedido | F94: cliente | G94: cliente | H94: cliente | I94: cliente | J94: cliente | K94: cliente | L94: cliente | M94: cliente | N94: cliente | O94: cliente | P94: cliente | Q94: cliente | R94: cliente | S94: cliente | T94: cliente | U94: cliente | V94: cliente | W94: cliente | X94: cliente | Y94: cliente | Z94: cliente | AA94: cliente | AB94: TOTAL
A95: =WEEKNUM("17/04/2025") -> 16 | B95: =catalog!B2 -> Nuez Mariposa Extra Light x 1 Kg | D95: =catalog!E2 -> 20500 | E95: =IF(sum(F95:AA95)>=1,"SI", "NO") -> NO | AB95: =sum(F95:AA95) -> 0
A96: =WEEKNUM("17/04/2025") -> 16 | B96: =catalog!B3 -> Almendra Non Pareil 27/30 x 1 Kg | D96: =catalog!E3 -> 23000 | E96: =IF(sum(F96:AA96)>=1,"SI", "NO") -> NO | AB96: =sum(F96:AA96) -> 0
A97: =WEEKNUM("17/04/2025") -> 16 | B97: =catalog!B4 -> Mani tostado con y sin sal PREMIUM x 1 Kg | D97: =catalog!E4 -> 3000 | E97: =IF(sum(F97:AA97)>=1,"SI", "NO") -> NO | AB97: =sum(F97:AA97) -> 0
A98: =WEEKNUM("17/04/2025") -> 16 | B98: =#REF! -> #REF! | D98: =#REF! -> #REF! | E98: =IF(sum(F98:AA98)>=1,"SI", "NO") -> NO | AB98: =sum(F98:AA98) -> 0
A99: =WEEKNUM("17/04/2025") -> 16 | B99: =catalog!B5 -> Nuez Pecan x 1 Kg | D99: =catalog!E5 -> 34600 | E99: =IF(sum(F99:AA99)>=1,"SI", "NO") -> NO | AB99: =sum(F99:AA99) -> 0
A100: =WEEKNUM("17/04/2025") -> 16 | B100: =catalog!B6 -> Cajú W4 brasilero x 1 Kg | D100: =catalog!E6 -> 19500 | E100: =IF(sum(F100:AA100)>=1,"SI", "NO") -> NO | AB100: =sum(F100:AA100) -> 0
...

Sheet PEDIDOS m y m
C1: Cliente | D1: Producto | E1: Cantidad | F1: Precio Unitario | G1: Total | I1: Notas (lugar)
A2: 45730 | C2: Cecilia (Lauti) | D2: Mix Premiun gourmet | E2: 1kg | F2: 17480 | G2: 17480 | I2: Area 10 Lote 268 SS | J2: pago
A3: 45730 | C3: Cecilia (Lauti) | D3: Quinoa | E3: 1kg | F3: 6900 | G3: 6900 | I3: Area 10 Lote 268 SS | J3: pago
A4: 15/3/25 | C4: Marianela (Laure) | D4: Mani Tostado sin sal | E4: 1kg | F4: 3000 | G4: 3000 | I4: Area 6 Lote 233 SS | J4: pago
A5: 15/3/25 | C5: Marianela (Laure) | D5: Mix Criollo o runner con banan | E5: 1kg | F5: 6500 | G5: 6500 | I5: Area 6 Lote 234 SS | J5: pago
A6: 17/3/25 | C6: Marcela Rivera | D6: Mix Criollo o runner con banan | E6: 1kg | F6: 6500 | G6: 6500 | I6: Area 2 Lote 6 SS | J6: Pago
A7: 17/3/25 | C7: Marcela Rivera | D7: Harina de Almendras sin piel | E7: 2 kg | F7: 4200 | G7: 4200 | H7: Separadas1kg y 1kg | I7: Area 2 Lote 6 SS | J7: Pago
A8: 17/3/25 | C8: Marcela Rivera | D8: Mermelada Los Carolinos Durazno | E8: 1 | F8: 4200 | G8: 3000 | I8: Area 2 Lote 6 SS | J8: Pago
A9: 17/3/25 | C9: Marcela Rivera | D9: Nuez Mariposa | E9: 1kg | F9: 20600 | G9: 20600 | I9: Area 2 Lote 6 SS | J9: Pago
A10: 17/3/25 | C10: Marcela Rivera | D10: Mani Tostado con sal | E10: 1kg | F10: 3000 | G10: 3000 | I10: Area 2 Lote 6 SS | J10: Pago
A11: 45734 | C11: Rosario | D11: Mix Premium gourmet (cajú, alm | E11: 1kg | F11: 18000 | G11: 18000 | I11: Area 1 Lote 479 | J11: Pago
A12: 45734 | C12: Rosario | D12: Pistachos con cascara | E12: 1kg | F12: 33000 | G12: 33000 | I12: Area 1 Lote 479 | J12: Pago
A13: 45734 | C13: Rosario | D13: Harina de Almendras con piel | E13: 1kg | F13: 4000 | G13: 4000 | I13: Area 1 Lote 479 | J13: Pago
C14: Marina yo | D14: Mani con sal | E14: 1kg | F14: 3000
C15: Marina yo | D15: Pistachos con cascara | E15: 1gr | F15: 33000
C16: Marina yo | D16: Mix Premium gourmet (cajú, alm | E16: 1kg | F16: 15500
C17: Marina yo | D17: Bananas disecadas | E17: 1kg | F17: 6400
C18: Marina yo | D18: Harina de coco | E18: 2kg | F18: 9200
C19: Marina yo | D19: Harina de Almendras | E19: 1kg | F19: 3400
C20: Marina yo | D20: Fecula de Mandioca | E20: 1kg
C21: Marina yo | D21: Aceite de coco neutro x 360 | E21: 1 unidad | F21: 3300
C22: Marina yo | D22: Chip chocolate | E22: 1gr | F22: 6600
C23: Marina yo | D23: Galletitas Nutresan sabor coco | E23: 1 una | F23: 1130
C24: Marina yo | D24: Galletitas Nutresan sabor algarroba | E24: 1 una | F24: 1140
C25: Saha | D25: Mix Premium gourmet (cajú, alm | E25: 1 kg | F25: 18000 | I25: pago
C26: Raul | D26: mani con sal | E26: 1 kg | F26: 3000 | I26: pago
D27: castañas caju | E27: 1 kg | F27: 12500
D28: arandanos | E28: 1 kg | F28: 10500
D29: mix semillas | E29: 1 kg | F29: 3000
D30: pasas con chocolate | E30: 1 kg | F30: 13200
C31: Gustavo | D31: Mix Premium gourmet (cajú, alm | E31: 2 kg | F31: 36000 | I31: pagó
C32: Gabi | D32: arandanos | E32: 2 kg | F32: 21000 | I32: pago
D33: castañas para | E33: 1 kg | F33: 19400
C34: Luciano | D34: arandanos | E34: 1 kg | F34: 10500 | I34: pagó
C35: yo | D35: nueces pecan | E35: 1 kg | F35: 17100
F36: =sum(F2:F35) -> 374250
A38: 45743
C39: Auri | D39: mix criollo con bananitas | E39: 1 | F39: 6700 | H39: 6000 | I39: pago
D40: mix criollo con bananitas | E40: 1 | F40: 6900 | H40: 6000
D41: mermelada naranja | E41: 1 | F41: 3000 | H41: 2200
D42: harina almendras sin piel | E42: 1 | F42: 4200 | H42: 3600
C43: Maiju | D43: mermelada sin azucar ciruela | E43: 1 | F43: 3000 | H43: 2200 | I43: pago
D44: mermelada sin azucar durazno | E44: 1 | F44: 3000 | H44: 2200
D45: aceite de coco neutro | E45: 1 | F45: 4000 | H45: 3300
C47: Luz | D47: nueces | E47: 1 | F47: 20600 | H47: 17900 | I47: pago
D48: castañas | E48: 1 | F48: 14200 | H48: 12300
D49: almendras | E49: 1 | F49: 17700 | H49: 15400
D50: arandanos | E50: 1 | F50: 10500 | H50: 7900
D51: quinoa | E51: 1 | F51: 6900 | H51: 6000
D52: harina mandioca | E52: 45779 | F52: 5000 | H52: 8000
C54: saha | D54: harina almendras con piel | E54: 1 | F54: 4000 | H54: 3400 | I54: pago
H55: 3900
C57: Gla | D57: roapipo suave | E57: 45689 | F57: 3100 | H57: 2700 | I57: pago
C59: karina | D59: harina almendras sin piel | E59: 1 | F59: 4200 | H59: 3600 | I59: pago
D60: tomates deshidratados | E60: 1 | F60: 14600 | H60: 12700
D61: nueces | E61: 1 | F61: 20600 | H61: 17900
C63: Vero | D63: almendras | E63: 1 | F63: 17700 | H63: 15400 | I63: pago
C65: Agustina | D65: nueces | E65: 2 | F65: 41200 | H65: 35800
D66: castañas | E66: 1 | F66: 14200 | H66: 12300
C68: yo | D68: caja ciruelas | E68: 1 | F68: 23940 | H68: 23940
D69: almendras | E69: 1 | F69: 15400 | H69: 15400
D70: harina almendras s piel | E70: 1 | F70: 3600 | H70: 3600
D71: yerba roapipo 1/2 | E71: 1 | F71: 2700
F72: =SUM(F39:F71) -> 270940 | H72: =SUM(H39:H69) -> 240040
C73: Marianela Area 6 | D73: Mix criollo CON BANANITAS | E73: 1 | F73: 6900 | G73: 6900 | I73: pago | J73: pago
C74: Marcela Rivera Area 2 | D74: Harina de Almendras SIN PIEL | E74: 2 | F74: 4200 | G74: 8400 | I74: pago | J74: pago
A76: 01 de abril
C77: Guadalupe Area 1 | D77: Harina de Almedras | E77: 1 | F77: 4200 | G77: 4200 | I77: pago
C78: Guadalupe Area 1 | D78: Harina de Avena | E78: 1 | F78: 1900 | G78: 1900 | I78: pago
C79: Guadalupe Area 1 | D79: Harina de coco | E79: 1 | F79: 5300 | G79: 5300 | I79: pago
C80: Marcela Rivaera Area 2 | D80: Mix criollo o runner con bananas | E80: 1 | F80: 6900 | G80: 6900 | I80: pago | J80: pago
C81: Marcela Rivaera Area 2 | D81: Tomates deshidratados | E81: 3 | F81: 14600 | G81: 43800 | I81: pago
C82: Marcela Rivaera Area 2 | D82: harina de avena | E82: 1 | F82: 1900 | G82: 1900 | I82: pago
C83: Marcela Rivaera Area 2 | D83: rocklets | E83: 1 | F83: 14400 | G83: 14400 | I83: pago
C84: Marcela Rivaera Area 2 | D84: chocolate alpino semiamargo | E84: 1 | F84: 4900 | G84: 4900 | I84: pago
C86: saha | D86: harina algarroba | E86: 1 | F86: 5000 | G86: 5000 | H86: 3900 | I86: pagó
C88: Naty nori | D88: mix premium | E88: 2 | F88: 18000 | G88: 36000 | H88: 31500 | I88: pago
D89: harina de almendras | E89: 1 | F89: 4000 | G89: 4000 | H89: 3600
D90: harina integral | E90: 1 | F90: 1100 | G90: 1100 | H90: 3900
D91: fecula mandioca | E91: 5 | F91: 11000 | G91: 11000 | H91: 8000
D92: granola premium crujiente | E92: 1 | F92: 5700 | H92: 4700
D93: mix semillas premium | E93: 1 | F93: 3000 | G93: 3000 | H93: 2600
D94: sesamo integral | E94: 1 | F94: 3200 | G94: 3200 | H94: 3400
D95: pasta mani | E95: 1 | F95: 2500
D96: arandanos | E96: 1 | F96: 10500 | G96: 10500 | H96: 7900
C98: Nori | D98: mani tostado con sal | E98: 1 | F98: 3000 | G98: 3000 | I98: pago
D99: chia | E99: 1 | F99: 4500 | G99: 4500 | H99: ver
D100: pasta mani crocante | E100: 1
C103: Nati gym | D103: almendras | E103: 1 | G103: 17700 | H103: 15400 | I103: pago
D104: mani tostado sin sal | E104: 1 | G104: 3000 | H104: 2500
D105: harina integral | E105: 1 | F105: 1100 | G105: 1100
D106: pasta mani | E106: 1 | F106: 2500
D107: aceite oliva | E107: 1 | F107: 8200 | G107: 8200 | H107: 6800
D108: te matcha | E108: 50 gr | F108: 1500 | G108: 1500 | H108: 2200
C110: mama nori | D110: harina almendras | G110: 4000 | H110: 3600 | I110: pago
D111: granola tropical | G111: 5400 | H111: 4500
D112: ciruelas | G112: 7000 | H112: 7000
D113: mix premium gourmet | G113: 18000 | H113: 15500
A115: 45754 | C115: agus | D115: harina coco | E115: 2 Kg | F115: 5300 | G115: 10600 | H115: =4600*2 -> 9200 | I115: pago
D116: arandanos | E116: 2 kg | F116: 10500 | G116: 21000 | H116: =7900*2 -> 15800
...

Sheet Hoja 7
